CHANGES.md
LICENSE.AGPL.md
LICENSE.md
MANIFEST.in
README.md
VERSION
pyproject.toml
requirements-devel.txt
requirements-docs.txt
requirements-tests.txt
requirements.txt
setup.py
examples/rc_process.py
src/rc.process.egg-info/PKG-INFO
src/rc.process.egg-info/SOURCES.txt
src/rc.process.egg-info/dependency_links.txt
src/rc.process.egg-info/not-zip-safe
src/rc.process.egg-info/top_level.txt
src/rc/process/VERSION
src/rc/process/__init__.py
src/rc/process/process.py